ai_agent/__init__.py
ai_agent/config.py
ai_agent/gpt_manager/__init__.py
ai_agent/gpt_manager/agent.py
ai_agent/tools/__init__.py
ai_agent/tools/file_manager.py
ai_agent/tools/tool_call_predictor.py
ai_agent/tools/tool_dispatcher.py
ai_agent/tools/tool_manager.py
ai_agent/tools/tools_collector.py
openai_agent_core-0.1.2.dist-info/licenses/LICENSE
openai_agent_core-0.1.2.dist-info/METADATA
openai_agent_core-0.1.2.dist-info/WHEEL
openai_agent_core-0.1.2.dist-info/top_level.txt
openai_agent_core-0.1.2.dist-info/RECORD
