Metadata-Version: 2.4
Name: openai-agent-core
Version: 0.1.2
Summary: GPT agent logic with tool calling and dispatching
Author-email: Платановский Дмитрий <you@example.com>
License: MIT
Keywords: GPT,OpenAI,agent,tool calling,tool dispatcher,AI,ML,asynchronous,LangChain,FastAPI,async,simple,tools
Classifier: Development Status :: 4 - Beta
Classifier: Intended Audience :: Developers
Classifier: Topic :: Software Development :: Libraries
Classifier: License :: OSI Approved :: MIT License
Classifier: Programming Language :: Python
Classifier: Programming Language :: Python :: 3
Classifier: Programming Language :: Python :: 3.9
Classifier: Programming Language :: Python :: 3.10
Classifier: Programming Language :: Python :: 3.11
Classifier: Programming Language :: Python :: 3.12
Classifier: Operating System :: OS Independent
Requires-Python: >=3.9
License-File: LICENSE
Requires-Dist: openai
Requires-Dist: scikit-learn
Requires-Dist: jsonschema
Requires-Dist: pydantic
Dynamic: license-file
